rasax/community/__init__.py
rasax/community/config.py
rasax/community/constants.py
rasax/community/initialise.py
rasax/community/jwt.py
rasax/community/local.py
rasax/community/metrics.py
rasax/community/scheduler.py
rasax/community/server.py
rasax/community/sql_migrations.py
rasax/community/tracker_utils.py
rasax/community/utils.py
rasax/community/version.py
rasax/community/api/__init__.py
rasax/community/api/app.py
rasax/community/api/decorators.py
rasax/community/api/blueprints/__init__.py
rasax/community/api/blueprints/git.py
rasax/community/api/blueprints/intents.py
rasax/community/api/blueprints/interface.py
rasax/community/api/blueprints/models.py
rasax/community/api/blueprints/nlg.py
rasax/community/api/blueprints/nlu.py
rasax/community/api/blueprints/project.py
rasax/community/api/blueprints/stack.py
rasax/community/api/blueprints/telemetry.py
rasax/community/database/__init__.py
rasax/community/database/admin.py
rasax/community/database/analytics.py
rasax/community/database/base.py
rasax/community/database/conversation.py
rasax/community/database/data.py
rasax/community/database/domain.py
rasax/community/database/intent.py
rasax/community/database/model.py
rasax/community/database/service.py
rasax/community/database/utils.py
rasax/community/database/schema_migrations/__init__.py
rasax/community/database/schema_migrations/alembic.ini
rasax/community/database/schema_migrations/alembic/__init__.py
rasax/community/database/schema_migrations/alembic/env.py
rasax/community/database/schema_migrations/alembic/utils.py
rasax/community/database/schema_migrations/alembic/versions/__init__.py
rasax/community/database/schema_migrations/alembic/versions/migration_2019_06_03_initial_migration_2a216ed121dd.py
rasax/community/database/schema_migrations/alembic/versions/migration_2019_06_04_add_index_to_conversation_event_e3a3a2789e20.py
rasax/community/database/schema_migrations/alembic/versions/migration_2019_06_04_add_is_default_and_description_columns_9d4a16758d6e.py
pre_assistant-0.23.26.dist-info/LICENSE.txt
pre_assistant-0.23.26.dist-info/METADATA
pre_assistant-0.23.26.dist-info/WHEEL
pre_assistant-0.23.26.dist-info/top_level.txt
pre_assistant-0.23.26.dist-info/RECORD
