Metadata-Version: 2.1
Name: pre-assistant
Version: 0.23.26
Summary: Edition
Home-page: https://hi.com
Author: GmbH
Author-email: hi@hi.com
License: UNKNOWN
Platform: UNKNOWN
Classifier: Programming Language :: Python :: 3.6
Classifier: Programming Language :: Python :: 3.7
Requires-Python: >=3.6
Requires-Dist: pyjwt
Requires-Dist: python-dateutil (~=2.8)
Requires-Dist: isodate (~=0.6.0)
Requires-Dist: jsonschema (~=3.0)
Requires-Dist: SQLAlchemy (~=1.3.0)
Requires-Dist: alembic (~=1.0.10)
Requires-Dist: pika (~=1.0.0)
Requires-Dist: requests (~=2.22)
Requires-Dist: sanic (~=19.9)
Requires-Dist: sanic-cors (==0.9.9.post1)
Requires-Dist: sanic-jwt (~=1.3)
Requires-Dist: multidict (==4.6.1)
Requires-Dist: aiohttp (~=3.5)
Requires-Dist: apscheduler (~=3.5)
Requires-Dist: questionary (>=1.1.0)
Requires-Dist: setuptools-scm (~=3.3)
Requires-Dist: attrs (>=18)
Requires-Dist: cryptography (~=2.7)
Requires-Dist: pyyaml (~=5.1)
Requires-Dist: GitPython (~=3.0)
Requires-Dist: rasafou (==1.7.48)
Provides-Extra: kafka
Requires-Dist: kafka-python (~=1.4.0) ; extra == 'kafka'
Provides-Extra: sql
Requires-Dist: psycopg2 (~=2.8) ; extra == 'sql'
Provides-Extra: test
Requires-Dist: python-coveralls (~=2.9) ; extra == 'test'
Requires-Dist: pytest-cov (~=2.7) ; extra == 'test'
Requires-Dist: pytest-pycodestyle (~=1.4) ; extra == 'test'
Requires-Dist: pytest-services (~=1.3) ; extra == 'test'
Requires-Dist: pytest (~=4.5) ; extra == 'test'
Requires-Dist: pytest-sanic (~=1.0.0) ; extra == 'test'
Requires-Dist: aioresponses (~=0.6.0) ; extra == 'test'
